bili_cli/__init__.py
bili_cli/api.py
bili_cli/apis/__init__.py
bili_cli/apis/base.py
bili_cli/apis/passport.py
bili_cli/app.py
bili_cli/base.py
bili_cli/bili/__init__.py
bili_cli/bili/base.py
bili_cli/bili/bili.py
bili_cli/bili/orm.py
bili_cli/bili/section_episode_sort.py
bili_cli/bookmark.py
bili_cli/cmd/__init__.py
bili_cli/cmd/app.py
bili_cli/cmd/archive.py
bili_cli/cmd/auth.py
bili_cli/cmd/base.py
bili_cli/cmd/config.py
bili_cli/cmd/config_user_album.py
bili_cli/cmd/config_video.py
bili_cli/cmd/download.py
bili_cli/cmd/episode.py
bili_cli/cmd/history.py
bili_cli/cmd/part.py
bili_cli/cmd/reply.py
bili_cli/cmd/season.py
bili_cli/command.py
bili_cli/common/__init__.py
bili_cli/common/bilibili/__init__.py
bili_cli/common/bilibili/client.py
bili_cli/common/bilibili/dto/__init__.py
bili_cli/common/bilibili/dto/acc_info.py
bili_cli/common/bilibili/dto/base.py
bili_cli/common/crud.py
bili_cli/common/mongo.py
bili_cli/config/__init__.py
bili_cli/config/album.py
bili_cli/config/celerys.py
bili_cli/config/config.py
bili_cli/config/make.py
bili_cli/config/season.py
bili_cli/config/settings.py
bili_cli/config/user.py
bili_cli/config/user_album.py
bili_cli/const/__init__.py
bili_cli/const/base.py
bili_cli/const/cmd.py
bili_cli/const/episode.py
bili_cli/const/episode_big_bang.py
bili_cli/const/episode_feiqi.py
bili_cli/const/episode_ipartment.py
bili_cli/const/episode_langyabang.py
bili_cli/const/episode_mos.py
bili_cli/const/episode_movie.py
bili_cli/const/episode_wanwan.py
bili_cli/const/image.py
bili_cli/const/reg.py
bili_cli/const/story.py
bili_cli/constants.py
bili_cli/db/context.py
bili_cli/db/orm.py
bili_cli/dto.py
bili_cli/dtos/__init__.py
bili_cli/dtos/album.py
bili_cli/dtos/archive.py
bili_cli/dtos/base.py
bili_cli/dtos/episode.py
bili_cli/dtos/history.py
bili_cli/dtos/qrcode.py
bili_cli/dtos/reply.py
bili_cli/dtos/season.py
bili_cli/dtos/user.py
bili_cli/init_db.py
bili_cli/main.py
bili_cli/make.py
bili_cli/manage.py
bili_cli/middlewares/__init__.py
bili_cli-0.1.1.dist-info/METADATA
bili_cli-0.1.1.dist-info/WHEEL
bili_cli-0.1.1.dist-info/entry_points.txt
bili_cli-0.1.1.dist-info/RECORD
