Metadata-Version: 2.3
Name: bili_cli
Version: 0.1.1
Summary: 
Author: wxnacy
Author-email: wxnacy@gmail.com
Requires-Python: >=3.11,<3.14
Classifier: Programming Language :: Python :: 3
Classifier: Programming Language :: Python :: 3.11
Classifier: Programming Language :: Python :: 3.12
Classifier: Programming Language :: Python :: 3.13
Requires-Dist: aiohttp (>=3.9.5,<4.0.0)
Requires-Dist: annotated-types (>=0.7.0,<0.8.0)
Requires-Dist: bilibili-sdk (>=0.1.0,<0.2.0)
Requires-Dist: celery[redis] (>=5.3.6,<6.0.0)
Requires-Dist: chardet (>=5.2.0,<6.0.0)
Requires-Dist: fastapi (>=0.104.1,<0.105.0)
Requires-Dist: ffmpeg-python (>=0.2.0,<0.3.0)
Requires-Dist: flower (>=2.0.1,<3.0.0)
Requires-Dist: gevent (>=24.2.1,<25.0.0)
Requires-Dist: h11 (>=0.14.0,<0.15.0)
Requires-Dist: librosa (>=0.10.1,<0.11.0)
Requires-Dist: line-profiler (>=4.1.2,<5.0.0)
Requires-Dist: loguru (>=0.7.2,<0.8.0)
Requires-Dist: matplotlib (>=3.8.2,<4.0.0)
Requires-Dist: motor (>=3.4.0,<4.0.0)
Requires-Dist: mutagen (>=1.47.0,<2.0.0)
Requires-Dist: opencv-python (>=4.9.0.80,<5.0.0.0)
Requires-Dist: pandas (>=1.5.2,<2.0.0)
Requires-Dist: plotext (>=5.2.8,<6.0.0)
Requires-Dist: prettytable (>=3.9.0,<4.0.0)
Requires-Dist: prompt-toolkit (>=3.0.47,<4.0.0)
Requires-Dist: psutil (>=5.9.7,<6.0.0)
Requires-Dist: pyautogui (>=0.9.54,<0.10.0)
Requires-Dist: pydantic (>=2.3.0,<3.0.0)
Requires-Dist: pydantic-core (>=2.18.4,<3.0.0)
Requires-Dist: pydantic-settings (>=2.3.1,<3.0.0)
Requires-Dist: pydub (>=0.25.1,<0.26.0)
Requires-Dist: pygame (>=2.5.2,<3.0.0)
Requires-Dist: pylrc (>=0.1.2,<0.2.0)
Requires-Dist: pymongo (>=4.6.2,<5.0.0)
Requires-Dist: pypinyin (>=0.49.0,<0.50.0)
Requires-Dist: pysrt (>=1.1.2,<2.0.0)
Requires-Dist: python-dotenv (>=1.0.1,<2.0.0)
Requires-Dist: qrcode[pil] (>=7.4.2,<8.0.0)
Requires-Dist: redis (>=5.0.3,<6.0.0)
Requires-Dist: requests (>=2.31.0,<3.0.0)
Requires-Dist: rich (>=13.7.1,<14.0.0)
Requires-Dist: schedule (>=1.2.1,<2.0.0)
Requires-Dist: scipy (>=1.12.0,<2.0.0)
Requires-Dist: sqlalchemy (>=2.0.23,<3.0.0)
Requires-Dist: tabulate (>=0.9.0,<0.10.0)
Requires-Dist: typer (>=0.9.0,<0.10.0)
Requires-Dist: uvicorn (>=0.30.1,<0.31.0)
Requires-Dist: wpy (>=0.7.4,<0.8.0)
